calculator_template/__init__.py
calculator_template/calculator.py
calculator_template-0.1.0.dist-info/METADATA
calculator_template-0.1.0.dist-info/WHEEL
calculator_template-0.1.0.dist-info/RECORD
