Metadata-Version: 2.1
Name: calculator_template
Version: 0.1.0
Summary: Calculator package
Author: tarun
Author-email: tarun1@gmail.com
Requires-Python: >=3.10,<4.0
Classifier: Programming Language :: Python :: 3
Classifier: Programming Language :: Python :: 3.10
Classifier: Programming Language :: Python :: 3.11
Classifier: Programming Language :: Python :: 3.12
